xxxlog/__init__.py
xxxlog/info.py
xxxlog-1.0.dist-info/LICENSE
xxxlog-1.0.dist-info/METADATA
xxxlog-1.0.dist-info/WHEEL
xxxlog-1.0.dist-info/top_level.txt
xxxlog-1.0.dist-info/RECORD
